wsdiff.py
wsdiff-0.3.2.dist-info/licenses/LICENSE.md
wsdiff-0.3.2.dist-info/METADATA
wsdiff-0.3.2.dist-info/WHEEL
wsdiff-0.3.2.dist-info/entry_points.txt
wsdiff-0.3.2.dist-info/top_level.txt
wsdiff-0.3.2.dist-info/RECORD
