Metadata-Version: 2.4
Name: wsdiff
Version: 0.3.2
Summary: wsdiff is a tool that produces a syntax-highlighted, self-contained, static HTML file that will show a colored, syntax-highlighted diff of two files or folders without external dependencies or javascript.
Author-email: jaseg <code@jaseg.de>
Project-URL: Source, https://git.jaseg.de/wsdiff.git
Project-URL: Bug Tracker, https://github.com/jaseg/wsdiff/issues
Classifier: Programming Language :: Python :: 3
Classifier: License :: OSI Approved :: MIT License
Classifier: Operating System :: OS Independent
Requires-Python: >=3.7
License-File: LICENSE.md
Requires-Dist: pygments
Requires-Dist: witchhazel
Dynamic: license-file
